nionctl/__init__.py
nionctl/lib/archive.py
nionctl/lib/bt.py
nionctl/lib/img.py
nionctl/lib/plb.py
nionctl/lib/util.py
nionctl/lib/wifi.py
nionctl/main.py
nionctl-0.2.5.1.dist-info/entry_points.txt
nionctl-0.2.5.1.dist-info/WHEEL
nionctl-0.2.5.1.dist-info/METADATA
nionctl-0.2.5.1.dist-info/RECORD
