Metadata-Version: 2.1
Name: nionctl
Version: 0.2.5.1
Summary: 
Author: 8Dion8
Author-email: shvartserinfo@gmail.com
Requires-Python: >=3.10,<4.0
Classifier: Programming Language :: Python :: 3
Classifier: Programming Language :: Python :: 3.10
Classifier: Programming Language :: Python :: 3.11
Requires-Dist: typer[all] (>=0.6.1,<0.7.0)
